completescraper/__init__.py
completescraper/http_session/__init__.py
completescraper/http_session/enums.py
completescraper/http_session/exceptions.py
completescraper/http_session/http_session.py
completescraper/parser/__init__.py
completescraper/parser/html_containers.py
completescraper-0.1.2.dist-info/METADATA
completescraper-0.1.2.dist-info/WHEEL
completescraper-0.1.2.dist-info/licenses/LICENSE
completescraper-0.1.2.dist-info/RECORD
